fondat/aws/athena.py
fondat/aws/bedrock/README.md
fondat/aws/bedrock/__init__.py
fondat/aws/bedrock/cache.py
fondat/aws/bedrock/clients.py
fondat/aws/bedrock/decorators.py
fondat/aws/bedrock/domain.py
fondat/aws/bedrock/pagination.py
fondat/aws/bedrock/resources/action_groups.py
fondat/aws/bedrock/resources/agent.py
fondat/aws/bedrock/resources/agents.py
fondat/aws/bedrock/resources/aliases.py
fondat/aws/bedrock/resources/collaborators.py
fondat/aws/bedrock/resources/flows.py
fondat/aws/bedrock/resources/generic_resources.py
fondat/aws/bedrock/resources/memory.py
fondat/aws/bedrock/resources/prompts.py
fondat/aws/bedrock/resources/sessions.py
fondat/aws/bedrock/resources/streams.py
fondat/aws/bedrock/resources/versions.py
fondat/aws/bedrock/utils.py
fondat/aws/client.py
fondat/aws/cloudwatch.py
fondat/aws/lambda_.py
fondat/aws/s3.py
fondat/aws/secretsmanager.py
fondat_aws-4.1.1.dist-info/LICENSE
fondat_aws-4.1.1.dist-info/METADATA
fondat_aws-4.1.1.dist-info/WHEEL
fondat_aws-4.1.1.dist-info/RECORD
