Metadata-Version: 2.1
Name: fondat-aws
Version: 4.1.1
Summary: Fondat package for Amazon Web Services.
Home-page: https://github.com/fondat/fondat-aws/
License: MIT
Keywords: asgi,foundation,resource,openapi
Author: fondat-aws authors
Requires-Python: >=3.11,<4.0
Classifier: Development Status :: 5 - Production/Stable
Classifier: Intended Audience :: Developers
Classifier: License :: OSI Approved :: MIT License
Classifier: Programming Language :: Python :: 3
Classifier: Programming Language :: Python :: 3.11
Classifier: Topic :: Software Development :: Libraries :: Application Frameworks
Requires-Dist: aiobotocore (>=2.5.0,<3.0.0)
Requires-Dist: fondat (>=4.1.15,<5.0.0)
Project-URL: Documentation, https://github.com/fondat/fondat-aws/wiki
